cursedforged/__init__.py
cursedforged/api/__init__.py
cursedforged/api/base.py
cursedforged/api/client.py
cursedforged/api/v1/__init__.py
cursedforged/api/v2/__init__.py
cursedforged/types/__init__.py
cursedforged/types/category.py
cursedforged/types/enums.py
cursedforged/types/files.py
cursedforged/types/fingerprints.py
cursedforged/types/games.py
cursedforged/types/minecraft.py
cursedforged/types/mods.py
cursedforged/types/responses.py
cursedforged-0.9.4.dist-info/METADATA
cursedforged-0.9.4.dist-info/WHEEL
cursedforged-0.9.4.dist-info/RECORD
