Metadata-Version: 2.1
Name: cursedforged
Version: 0.9.4
Summary: CurseForge API Wrapper
Author: tengueax
Author-email: tengueax@tutamail.com
Requires-Python: >=3.12,<4.0
Classifier: Programming Language :: Python :: 3
Classifier: Programming Language :: Python :: 3.12
Requires-Dist: pydantic (>=2.8.2,<3.0.0)
Requires-Dist: requests (>=2.32.3,<3.0.0)
